README.rst
setup.py
evecentral/__init__.py
evecentral.egg-info/PKG-INFO
evecentral.egg-info/SOURCES.txt
evecentral.egg-info/dependency_links.txt
evecentral.egg-info/top_level.txt