Metadata-Version: 1.1
Name: evecentral
Version: 0.0.1
Summary: A small module to cache eve central prices in memory
Home-page: https://github.com/ZymoticB/python-evecentral
Author: Tyler Dixon
Author-email: tyler@chlystyk.com
License: BSD
Keywords: eve evecentral
Platform: UNKNOWN
Classifier: Development Status :: 3 - Alpha
Classifier: Intended Audience :: Developers
Classifier: License :: OSI Approved :: BSD License
Classifier: Topic :: Games/Entertainment
Classifier: Topic :: Software Development :: Libraries
